{"success": true, "data": [{"challenge_id": 17, "id": 20175, "date": "2025-07-06T16:30:27.127376+00:00", "user": {"id": 128, "name": "rootforcee"}, "type": "correct", "team": {"id": 79, "name": "rootforcee"}, "challenge": {"category": "Forensics", "id": 17, "name": "Blitz Traffic", "value": 100}}, {"challenge_id": 81, "id": 19971, "date": "2025-07-06T16:19:06.539425+00:00", "user": {"id": 128, "name": "rootforcee"}, "type": "correct", "team": {"id": 79, "name": "rootforcee"}, "challenge": {"category": "Misc", "id": 81, "name": "\ud83e\udd76\ud83e\udd75\ud83e\udd76\ud83e\udd75\ud83e\udd76\ud83e\udd75", "value": 480}}, {"challenge_id": 82, "id": 19204, "date": "2025-07-06T15:30:11.192922+00:00", "user": {"id": 128, "name": "rootforcee"}, "type": "correct", "team": {"id": 79, "name": "rootforcee"}, "challenge": {"category": "Misc", "id": 82, "name": "BlitzBot", "value": 323}}, {"challenge_id": 84, "id": 19019, "date": "2025-07-06T15:13:22.260793+00:00", "user": {"id": 128, "name": "rootforcee"}, "type": "correct", "team": {"id": 79, "name": "rootforcee"}, "challenge": {"category": "Web", "id": 84, "name": "Unstoppable force meets immovable object 2", "value": 159}}, {"challenge_id": 43, "id": 16136, "date": "2025-07-06T12:23:31.871784+00:00", "user": {"id": 128, "name": "rootforcee"}, "type": "correct", "team": {"id": 79, "name": "rootforcee"}, "challenge": {"category": "Crypto", "id": 43, "name": "Maffs", "value": 460}}, {"challenge_id": 71, "id": 15718, "date": "2025-07-06T11:54:29.474283+00:00", "user": {"id": 128, "name": "rootforcee"}, "type": "correct", "team": {"id": 79, "name": "rootforcee"}, "challenge": {"category": "Web", "id": 71, "name": "Fleg Store 2.0", "value": 50}}, {"challenge_id": 27, "id": 15365, "date": "2025-07-06T11:28:11.858109+00:00", "user": {"id": 128, "name": "rootforcee"}, "type": "correct", "team": {"id": 79, "name": "rootforcee"}, "challenge": {"category": "Misc", "id": 27, "name": "Duck\u2019s Revenge", "value": 262}}, {"challenge_id": 30, "id": 15231, "date": "2025-07-06T11:14:47.409808+00:00", "user": {"id": 128, "name": "rootforcee"}, "type": "correct", "team": {"id": 79, "name": "rootforcee"}, "challenge": {"category": "Misc", "id": 30, "name": "Hidden Signal in Noise", "value": 63}}, {"challenge_id": 64, "id": 15073, "date": "2025-07-06T11:01:48.356768+00:00", "user": {"id": 128, "name": "rootforcee"}, "type": "correct", "team": {"id": 79, "name": "rootforcee"}, "challenge": {"category": "Web", "id": 64, "name": "Middle of nowhere", "value": 50}}, {"challenge_id": 42, "id": 12930, "date": "2025-07-06T08:45:58.934183+00:00", "user": {"id": 128, "name": "rootforcee"}, "type": "correct", "team": {"id": 79, "name": "rootforcee"}, "challenge": {"category": "Crypto", "id": 42, "name": "Fiboz-cryption", "value": 412}}, {"challenge_id": 52, "id": 11210, "date": "2025-07-06T06:40:02.698740+00:00", "user": {"id": 128, "name": "rootforcee"}, "type": "correct", "team": {"id": 79, "name": "rootforcee"}, "challenge": {"category": "OSINT", "id": 52, "name": "The Lost Dog", "value": 375}}, {"challenge_id": 47, "id": 10617, "date": "2025-07-06T06:09:22.809008+00:00", "user": {"id": 128, "name": "rootforcee"}, "type": "correct", "team": {"id": 79, "name": "rootforcee"}, "challenge": {"category": "OSINT", "id": 47, "name": "Wildlife", "value": 159}}, {"challenge_id": 28, "id": 9769, "date": "2025-07-06T04:43:18.295420+00:00", "user": {"id": 128, "name": "rootforcee"}, "type": "correct", "team": {"id": 79, "name": "rootforcee"}, "challenge": {"category": "Misc", "id": 28, "name": "Language of Madness", "value": 50}}, {"challenge_id": 58, "id": 9432, "date": "2025-07-06T03:42:28.092016+00:00", "user": {"id": 128, "name": "rootforcee"}, "type": "correct", "team": {"id": 79, "name": "rootforcee"}, "challenge": {"category": "Hardware", "id": 58, "name": "Redstone Logic 2", "value": 50}}, {"challenge_id": 35, "id": 8820, "date": "2025-07-06T01:34:35.220799+00:00", "user": {"id": 128, "name": "rootforcee"}, "type": "correct", "team": {"id": 79, "name": "rootforcee"}, "challenge": {"category": "Crypto", "id": 35, "name": "Custom RSA? - Revenge", "value": 280}}, {"challenge_id": 45, "id": 8810, "date": "2025-07-06T01:29:51.997972+00:00", "user": {"id": 128, "name": "rootforcee"}, "type": "correct", "team": {"id": 79, "name": "rootforcee"}, "challenge": {"category": "Crypto", "id": 45, "name": "Lightning Strike", "value": 100}}, {"challenge_id": 20, "id": 6183, "date": "2025-07-05T18:59:32.815786+00:00", "user": {"id": 128, "name": "rootforcee"}, "type": "correct", "team": {"id": 79, "name": "rootforcee"}, "challenge": {"category": "Forensics", "id": 20, "name": "The Warrior's Legacy #1", "value": 50}}, {"challenge_id": 40, "id": 5851, "date": "2025-07-05T18:36:26.602858+00:00", "user": {"id": 128, "name": "rootforcee"}, "type": "correct", "team": {"id": 79, "name": "rootforcee"}, "challenge": {"category": "Crypto", "id": 40, "name": "Randomized Chaos", "value": 315}}, {"challenge_id": 39, "id": 5443, "date": "2025-07-05T18:15:03.542402+00:00", "user": {"id": 128, "name": "rootforcee"}, "type": "correct", "team": {"id": 79, "name": "rootforcee"}, "challenge": {"category": "Crypto", "id": 39, "name": "Custom RSA", "value": 212}}, {"challenge_id": 41, "id": 3210, "date": "2025-07-05T16:28:56.834455+00:00", "user": {"id": 128, "name": "rootforcee"}, "type": "correct", "team": {"id": 79, "name": "rootforcee"}, "challenge": {"category": "Crypto", "id": 41, "name": "Broken encoding or what?", "value": 50}}, {"challenge_id": 68, "id": 2633, "date": "2025-07-05T16:04:04.300342+00:00", "user": {"id": 128, "name": "rootforcee"}, "type": "correct", "team": {"id": 79, "name": "rootforcee"}, "challenge": {"category": "Web", "id": 68, "name": "Fleg Store", "value": 50}}, {"challenge_id": 70, "id": 2544, "date": "2025-07-05T16:00:30.785542+00:00", "user": {"id": 128, "name": "rootforcee"}, "type": "correct", "team": {"id": 79, "name": "rootforcee"}, "challenge": {"category": "Web", "id": 70, "name": "Unstoppable force meets immovable object", "value": 50}}, {"challenge_id": 55, "id": 2355, "date": "2025-07-05T15:53:20.317016+00:00", "user": {"id": 128, "name": "rootforcee"}, "type": "correct", "team": {"id": 79, "name": "rootforcee"}, "challenge": {"category": "Hardware", "id": 55, "name": "Redstone Logic 1", "value": 50}}, {"challenge_id": 46, "id": 1137, "date": "2025-07-05T15:13:13.231894+00:00", "user": {"id": 128, "name": "rootforcee"}, "type": "correct", "team": {"id": 79, "name": "rootforcee"}, "challenge": {"category": "OSINT", "id": 46, "name": "Hacked by Kids Part 1", "value": 50}}], "meta": {"count": 24}}
