{"success": true, "data": [{"challenge_id": 84, "id": 20037, "date": "2025-07-06T16:22:54.047649+00:00", "user": {"id": 902, "name": "Sunshine"}, "type": "correct", "team": {"id": 493, "name": "echo \"Oops!\""}, "challenge": {"category": "Web", "id": 84, "name": "Unstoppable force meets immovable object 2", "value": 159}}, {"challenge_id": 40, "id": 17151, "date": "2025-07-06T13:07:29.507886+00:00", "user": {"id": 902, "name": "Sunshine"}, "type": "correct", "team": {"id": 493, "name": "echo \"Oops!\""}, "challenge": {"category": "Crypto", "id": 40, "name": "Randomized Chaos", "value": 315}}, {"challenge_id": 45, "id": 16634, "date": "2025-07-06T12:43:22.553919+00:00", "user": {"id": 902, "name": "Sunshine"}, "type": "correct", "team": {"id": 493, "name": "echo \"Oops!\""}, "challenge": {"category": "Crypto", "id": 45, "name": "Lightning Strike", "value": 100}}, {"challenge_id": 64, "id": 14478, "date": "2025-07-06T10:32:07.160037+00:00", "user": {"id": 877, "name": "Saturn_08"}, "type": "correct", "team": {"id": 493, "name": "echo \"Oops!\""}, "challenge": {"category": "Web", "id": 64, "name": "Middle of nowhere", "value": 50}}, {"challenge_id": 47, "id": 14098, "date": "2025-07-06T10:14:08.362485+00:00", "user": {"id": 902, "name": "Sunshine"}, "type": "correct", "team": {"id": 493, "name": "echo \"Oops!\""}, "challenge": {"category": "OSINT", "id": 47, "name": "Wildlife", "value": 159}}, {"challenge_id": 71, "id": 14016, "date": "2025-07-06T10:08:27.463452+00:00", "user": {"id": 877, "name": "Saturn_08"}, "type": "correct", "team": {"id": 493, "name": "echo \"Oops!\""}, "challenge": {"category": "Web", "id": 71, "name": "Fleg Store 2.0", "value": 50}}, {"challenge_id": 46, "id": 6496, "date": "2025-07-05T19:24:18.181999+00:00", "user": {"id": 902, "name": "Sunshine"}, "type": "correct", "team": {"id": 493, "name": "echo \"Oops!\""}, "challenge": {"category": "OSINT", "id": 46, "name": "Hacked by Kids Part 1", "value": 50}}, {"challenge_id": 70, "id": 5035, "date": "2025-07-05T17:52:53.553767+00:00", "user": {"id": 902, "name": "Sunshine"}, "type": "correct", "team": {"id": 493, "name": "echo \"Oops!\""}, "challenge": {"category": "Web", "id": 70, "name": "Unstoppable force meets immovable object", "value": 50}}, {"challenge_id": 55, "id": 3677, "date": "2025-07-05T16:47:14.109335+00:00", "user": {"id": 877, "name": "Saturn_08"}, "type": "correct", "team": {"id": 493, "name": "echo \"Oops!\""}, "challenge": {"category": "Hardware", "id": 55, "name": "Redstone Logic 1", "value": 50}}, {"challenge_id": 41, "id": 2615, "date": "2025-07-05T16:02:56.879123+00:00", "user": {"id": 877, "name": "Saturn_08"}, "type": "correct", "team": {"id": 493, "name": "echo \"Oops!\""}, "challenge": {"category": "Crypto", "id": 41, "name": "Broken encoding or what?", "value": 50}}], "meta": {"count": 10}}
